caapi_shared/schemas.py
caapi_shared/utils.py
caapi_shared-1.0.4.dist-info/WHEEL
caapi_shared-1.0.4.dist-info/METADATA
caapi_shared-1.0.4.dist-info/RECORD
