Metadata-Version: 2.1
Name: caapi-shared
Version: 1.0.4
Summary: Shared library for all services that are part of the VA-administered Claims Attributes API
Author: Nat Hillard
Author-email: nathaniel.hillard@va.gov
Requires-Python: >=3.8,<4.0
Classifier: Programming Language :: Python :: 3
Classifier: Programming Language :: Python :: 3.8
Classifier: Programming Language :: Python :: 3.9
Requires-Dist: pydantic (>=1.7.3,<2.0.0)
